{
  "あ": [
    "あいさつ",
    "あさひ",
    "あした",
    "あたま",
    "あめ",
    "あり",
    "あさ",
    "あくび",
    "あご",
    "あぶら",
    "あな",
    "あじ",
    "あわ",
    "あさがお",
    "あひる",
    "あさゆう",
    "あんこ",
    "あさつゆ",
    "あおぞら",
    "あいず",
    "あめりか",
    "あさせ",
    "あかつき",
    "あまど",
    "あきち",
    "あゆみ",
    "あぶらえ",
    "あまやどり",
    "あまぐも",
    "あきや"
  ],
  "い": [
    "いす",
    "いぬ",
    "いえ",
    "いろ",
    "いど",
    "いた",
    "いき",
    "いのち",
    "いちご",
    "いわし",
    "いりぐち",
    "いいわけ",
    "いちば",
    "いなか",
    "いとこ",
    "いっぽ",
    "いくじ",
    "いずみ",
    "いんど",
    "いかだ",
    "いねむり",
    "いろがみ",
    "いなずま",
    "いろえんぴつ",
    "いいだこ",
    "いとまき",
    "いねかり",
    "いっしょう"
  ],
  "う": [
    "うみ",
    "うた",
    "うえ",
    "うさぎ",
    "うちわ",
    "うそ",
    "うで",
    "うま",
    "うろこ",
    "うがい",
    "うちがわ",
    "うんが",
    "うたごえ",
    "うきわ",
    "うわぎ",
    "うらない",
    "うるぐあい",
    "うちゅう",
    "うでどけい",
    "うらにわ",
    "うきぶくろ",
    "うちあげ",
    "うわさ",
    "うちゅうふく",
    "うんどう",
    "うらぐち"
  ],
  "え": [
    "えき",
    "えんき",
    "えだ",
    "えがお",
    "えもの",
    "えんぴつ",
    "えいが",
    "えいご",
    "えさ",
    "えり",
    "えのぐ",
    "えび",
    "えびふらい",
    "えんとつ",
    "えいせい",
    "えんそく",
    "えんかい",
    "えいよう",
    "えんぜつ",
    "えくぼ",
    "えりまき",
    "えんげき",
    "えんそう",
    "えだまめ",
    "えきまえ",
    "えいゆう",
    "えんじ",
    "えのき",
    "えじぷと",
    "えがき",
    "えいぞう",
    "えいきゅう",
    "えんぴつけずり",
    "えだは",
    "えもじ",
    "えつけ",
    "えほうまき",
    "えりあ"
  ],
  "お": [
    "おかし",
    "おふろ",
    "おかね",
    "おに",
    "おと",
    "おとうと",
    "おび",
    "おかず",
    "おくじょう",
    "おんがく",
    "おひさま",
    "おおかみ",
    "おおぞら",
    "おまつり",
    "おみやげ",
    "おやつ",
    "おりがみ",
    "おうさま",
    "おかざり",
    "おかゆ",
    "おたまじゃくし",
    "おてつだい",
    "おとしだま",
    "おとぎばなし",
    "おんど",
    "おわり",
    "おくりもの",
    "おうこく",
    "おいわい",
    "おくさま",
    "おらんだ",
    "おおあめ",
    "おおどおり",
    "おんかい",
    "おてあらい",
    "おおすじ",
    "おくば",
    "おうふく",
    "おかいもの",
    "おいたち"
  ],
  "か": [
    "かさ",
    "かみ",
    "かお",
    "かぜ",
    "かめ",
    "かたすみ",
    "かがみ",
    "かおいろ",
    "かようび",
    "かぶと",
    "かえる",
    "かみなり",
    "かたち",
    "からす",
    "かたみち",
    "かくれんぼ",
    "かたつむり",
    "かるた",
    "かいすいよく",
    "かんこく",
    "かいがら",
    "かぶしき",
    "かていか",
    "かようきょく",
    "かみくず",
    "かたおもい",
    "かるがも",
    "かいすい",
    "かぶぬし"
  ],
  "き": [
    "きつね",
    "きって",
    "きのこ",
    "きもの",
    "きかい",
    "きせつ",
    "きゅうり",
    "きろく",
    "きもち",
    "きつつき",
    "きんいろ",
    "きゅうけい",
    "きぬ",
    "きどう",
    "きおく",
    "きたかぜ",
    "きっぷ",
    "きゅうしょく",
    "きょうしつ",
    "きんようび",
    "きょうだい",
    "きゃく",
    "きもだめし",
    "きふ",
    "きせき",
    "きぼう"
  ],
  "く": [
    "くつ",
    "くも",
    "くるま",
    "くじら",
    "くさ",
    "くり",
    "くうき",
    "くすり",
    "くちびる",
    "くだもの",
    "くろう",
    "くうこう",
    "くしゃみ",
    "くらげ",
    "くつした",
    "くふう",
    "くまで",
    "くろあちあ",
    "くつべら",
    "くうそう",
    "くぎ",
    "くらやみ",
    "くだり",
    "くちべに",
    "くうふく",
    "くろまめ",
    "くわがた"
  ],
  "け": [
    "けいと",
    "けむり",
    "けしき",
    "けが",
    "けいさつ",
    "けんか",
    "けしごむ",
    "けいかく",
    "けもの",
    "けいたい",
    "けんこう",
    "けいば",
    "けむし",
    "けらい",
    "けいこ",
    "けいろ",
    "けにあ",
    "けいれき",
    "けしょう",
    "けつえき",
    "けんきゅう",
    "けんちく",
    "けいひ",
    "けんぶつ",
    "けものみち",
    "けいび"
  ],
  "こ": [
    "こおり",
    "こども",
    "こんぶ",
    "こしょう",
    "ことば",
    "こおろぎ",
    "こうもり",
    "こんにゃく",
    "こづつみ",
    "こたつ",
    "こびと",
    "こむぎこ",
    "こねこ",
    "こうすい",
    "こんげつ",
    "こんご",
    "こくもつ",
    "こうずい",
    "こうつう",
    "こうか",
    "こうがい",
    "こうし",
    "こな",
    "こうもく",
    "こもりうた"
  ],
  "さ": [
    "さかな",
    "さくら",
    "さいふ",
    "さとう",
    "さんぽ",
    "さかい",
    "さる",
    "さいころ",
    "さかだち",
    "さんすう",
    "さかみち",
    "さつまいも",
    "さんかく",
    "さかば",
    "さいのう",
    "さうじあらびあ",
    "さくらんぼ",
    "さいしゅう",
    "さぎょう",
    "さくもつ",
    "さんせい",
    "さんぷく",
    "さとおや",
    "さゆう",
    "さんこう"
  ],
  "し": [
    "しか",
    "しお",
    "しま",
    "しあい",
    "しっぽ",
    "しずく",
    "しまうま",
    "しあわせ",
    "しごと",
    "しろくま",
    "しゃかい",
    "しゅくだい",
    "しょくじ",
    "しあげ",
    "しぶき",
    "しあさって",
    "しっけ",
    "しゅみ",
    "しんせつ",
    "しらが",
    "しっそ",
    "しんゆう",
    "しゃしょう",
    "しつけ",
    "しゅくはく",
    "しほう"
  ],
  "す": [
    "すいか",
    "すな",
    "すみれ",
    "すいとう",
    "すずめ",
    "すもう",
    "すいえい",
    "すうじ",
    "すいどう",
    "すきま",
    "すべりだい",
    "すもも",
    "すいせい",
    "すいちゅう",
    "すし",
    "すいす",
    "すあし",
    "すなば",
    "すきやき",
    "すずしさ",
    "すぱいす",
    "すあな",
    "すぎ",
    "すじみち",
    "すもうべや"
  ],
  "せ": [
    "せかい",
    "せみ",
    "せなか",
    "せんぷうき",
    "せいふく",
    "せんせい",
    "せいざ",
    "せんたく",
    "せともの",
    "せいり",
    "せんべい",
    "せいふ",
    "せびろ",
    "せおよぎ",
    "せんろ",
    "せるびあ",
    "せいと",
    "せいけつ",
    "せんぱい",
    "せいこう",
    "せいめい",
    "せみしぐれ",
    "せんぬき",
    "せびれ",
    "せいさく"
  ],
  "そ": [
    "そら",
    "そば",
    "そうじ",
    "そふ",
    "そぼ",
    "そうこ",
    "そつぎょう",
    "そくど",
    "そうぞう",
    "そまつ",
    "そうしき",
    "そうさ",
    "そこ",
    "そで",
    "そんとく",
    "そざい",
    "そまりあ",
    "そつぎょうしき",
    "そうべつかい",
    "そうがんきょう",
    "そうりつ",
    "そぼく",
    "そくたつ",
    "そうべつ",
    "そとがわ",
    "そざつ"
  ],
  "た": [
    "たいこ",
    "たまご",
    "たいよう",
    "たから",
    "たぬき",
    "たいふう",
    "たいせつ",
    "たまねぎ",
    "たんじょうび",
    "たき",
    "たいそう",
    "たこ",
    "たすき",
    "たいかい",
    "たいじゅう",
    "たい",
    "たいいく",
    "たいじ",
    "たいこう",
    "たなばた",
    "たてもの",
    "たびびと",
    "たからもの",
    "たいりょく",
    "たきび"
  ],
  "ち": [
    "ちず",
    "ちから",
    "ちいき",
    "ちゃいろ",
    "ちきゅう",
    "ちこく",
    "ちほう",
    "ちのう",
    "ちりょう",
    "ちきゅうぎ",
    "ちりがみ",
    "ちゃくち",
    "ちしき",
    "ちゃづけ",
    "ちえ",
    "ちゅうごく",
    "ちゅうしゃじょう",
    "ちからもち",
    "ちゅうい",
    "ちゃのゆ",
    "ちゃばたけ",
    "ちゃくりく",
    "ちしつ",
    "ちのけ",
    "ちゃかい"
  ],
  "つ": [
    "つき",
    "つくえ",
    "つばさ",
    "つゆ",
    "つばめ",
    "つな",
    "つの",
    "つみき",
    "つなみ",
    "つりばし",
    "つえ",
    "つづみ",
    "つばき",
    "つきひ",
    "つうやく",
    "つきみ",
    "つりぼり",
    "つちふまず",
    "つくりばなし",
    "つうろ",
    "つごう",
    "つみたて",
    "つなひき",
    "つゆどき",
    "つきよ"
  ],
  "て": [
    "てがみ",
    "てぶくろ",
    "てんき",
    "てつぼう",
    "てのひら",
    "てんし",
    "てんらんかい",
    "てじな",
    "てすり",
    "てちょう",
    "てんとうむし",
    "てんごく",
    "てあらい",
    "てつどう",
    "てんさい",
    "てあし",
    "てすうりょう",
    "てつがく",
    "てづくり",
    "てんじょう",
    "てんこう",
    "てさぎょう",
    "てさげ",
    "てつづき",
    "てふだ"
  ],
  "と": [
    "とけい",
    "とり",
    "とうふ",
    "とかげ",
    "とびら",
    "とうだい",
    "となり",
    "とうもろこし",
    "とんぼ",
    "とうげ",
    "とくい",
    "とかい",
    "とんかつ",
    "とびばこ",
    "とうろう",
    "とるこ",
    "とうちゃく",
    "とうひょう",
    "とけいだい",
    "とうけい",
    "とちゅう",
    "とっきゅう",
    "とうぶ",
    "とだな",
    "とうふや"
  ],
  "な": [
    "なつ",
    "なみ",
    "なべ",
    "なし",
    "なみだ",
    "なぞなぞ",
    "なわとび",
    "なまえ",
    "なっとう",
    "なかま",
    "なだれ",
    "なやみ",
    "なつやすみ",
    "なめくじ",
    "なんきょく",
    "ながぐつ",
    "なつまつり",
    "なわばり",
    "なやみごと",
    "なかにわ",
    "なべもの",
    "なみき",
    "ながそで",
    "なまり",
    "なかゆび"
  ],
  "に": [
    "にわ",
    "にじ",
    "にく",
    "にもつ",
    "にんぎょう",
    "にがおえ",
    "にちようび",
    "にゅうがく",
    "にっき",
    "にぼし",
    "にんき",
    "にもの",
    "にかい",
    "にゅうよく",
    "にちじょう",
    "にくじゃが",
    "にわとり",
    "にっちゅう",
    "にゅうし",
    "にもつだな",
    "にんずう",
    "にっか",
    "にっこう",
    "にんい",
    "にんてい"
  ],
  "ぬ": [
    "ぬの",
    "ぬま",
    "ぬいぐるみ",
    "ぬかみそ",
    "ぬりえ",
    "ぬくもり",
    "ぬけみち",
    "ぬいめ",
    "ぬかづけ",
    "ぬすびと",
    "ぬのじ",
    "ぬりぐすり",
    "ぬかるみ",
    "ぬかどこ",
    "ぬりばし",
    "ぬのぎれ",
    "ぬきあし",
    "ぬすみぎき",
    "ぬまべ",
    "ぬけがら",
    "ぬりもの",
    "ぬいばり",
    "ぬいしろ",
    "ぬまち",
    "ぬくみ",
    "ぬすっと",
    "ぬかあめ",
    "ぬのこ"
  ],
  "ね": [
    "ねこ",
    "ねつ",
    "ねいろ",
    "ねぼう",
    "ねずみ",
    "ねびき",
    "ねまき",
    "ねんど",
    "ねっとう",
    "ねいき",
    "ねぶそく",
    "ねうち",
    "ねまわし",
    "ねんれい",
    "ねぶくろ",
    "ねぱある",
    "ねつぞう",
    "ねずみいろ",
    "ねばりけ",
    "ねこじた",
    "ねぼすけ",
    "ねんが",
    "ねんし",
    "ねびえ",
    "ねぐせ"
  ],
  "の": [
    "のはら",
    "のど",
    "のこぎり",
    "のうか",
    "のみもの",
    "のりもの",
    "のうりょく",
    "のうぎょう",
    "のき",
    "のろし",
    "のばら",
    "のぼり",
    "のきした",
    "のうやく",
    "のこり",
    "のうこう",
    "のじゅく",
    "のづら",
    "のきさき",
    "のうにゅう",
    "のぼりざか",
    "のうしゅく",
    "のぞみ",
    "のきなみ",
    "のら"
  ],
  "は": [
    "はな",
    "はし",
    "はこ",
    "はさみ",
    "はたけ",
    "はちみつ",
    "はいざら",
    "はなび",
    "はがき",
    "はくちょう",
    "はいく",
    "はんかち",
    "はしご",
    "はやし",
    "はちまき",
    "はいゆう",
    "はなたば",
    "はくらんかい",
    "はしわたし",
    "はつゆき",
    "はなみず",
    "はいたつ",
    "はんそで",
    "はちうえ",
    "はんが"
  ],
  "ひ": [
    "ひかり",
    "ひまわり",
    "ひこうき",
    "ひたい",
    "ひも",
    "ひざ",
    "ひばな",
    "ひなまつり",
    "ひつじ",
    "ひろば",
    "ひやけ",
    "ひがし",
    "ひとみ",
    "ひげ",
    "ひづけ",
    "ひきだし",
    "ひざし",
    "ひとりごと",
    "ひやけどめ",
    "ひみつ",
    "ひなたぼっこ",
    "ひづめ",
    "ひろま",
    "ひとがら",
    "ひきにく"
  ],
  "ふ": [
    "ふね",
    "ふゆ",
    "ふくろ",
    "ふえ",
    "ふうふ",
    "ふもと",
    "ふきのとう",
    "ふくろう",
    "ふだ",
    "ふともも",
    "ふしぎ",
    "ふうけい",
    "ふうとう",
    "ふきそく",
    "ふくつう",
    "ふくすう",
    "ふうりょく",
    "ふくざつ",
    "ふしめ",
    "ふきかえ",
    "ふろしき",
    "ふたご",
    "ふくわらい",
    "ふくびき",
    "ふくじゅう",
    "ふきゅう",
    "ふとうこう",
    "ふしんせつ",
    "ふらんす",
    "ふでばこ",
    "ふうふげんか",
    "ふゆやすみ",
    "ふくわじゅつ",
    "ふでさき",
    "ふくぶくろ",
    "ふたり",
    "ふりこ",
    "ふきそうじ"
  ],
  "へ": [
    "へや",
    "へび",
    "へそ",
    "へいわ",
    "へんじ",
    "へいたい",
    "へだたり",
    "へちま",
    "へきが",
    "へんこう",
    "へんきゃく",
    "へいじつ",
    "へいや",
    "へんとう",
    "へいこう",
    "へいさ",
    "へんかく",
    "へそくり",
    "へいねつ",
    "へだて",
    "へいき",
    "へた",
    "へんぴ",
    "へんきょう",
    "へいち"
  ],
  "ほ": [
    "ほし",
    "ほうき",
    "ほたる",
    "ほほ",
    "ほね",
    "ほうせき",
    "ほうちょう",
    "ほしぞら",
    "ほうたい",
    "ほとけ",
    "ほうがく",
    "ほくろ",
    "ほうそう",
    "ほんだな",
    "ほいく",
    "ほうこく",
    "ほうりつ",
    "ほんばこ",
    "ほおづえ",
    "ほしくず",
    "ほどう",
    "ほのお",
    "ほうもんぎ",
    "ほんもの",
    "ほりばた"
  ],
  "ま": [
    "まど",
    "まくら",
    "まめ",
    "まつり",
    "まほう",
    "まいご",
    "まんげつ",
    "まないた",
    "まゆげ",
    "まいにち",
    "まほうつかい",
    "まつぼっくり",
    "まと",
    "まさつ",
    "まぐろ",
    "まれいしあ",
    "まいすう",
    "まちがい",
    "まつげ",
    "まちかど",
    "まちあわせ",
    "まきずし",
    "まつたけ",
    "まくらもと",
    "まがりかど"
  ],
  "み": [
    "みず",
    "みなと",
    "みどり",
    "みぎ",
    "みせ",
    "みみ",
    "みそしる",
    "みちしるべ",
    "みらい",
    "みずうみ",
    "みかづき",
    "みつばち",
    "みはらし",
    "みなみ",
    "みやげ",
    "みつご",
    "みなもと",
    "みはり",
    "みずたまり",
    "みつもり",
    "みぶり",
    "みぞ",
    "みつけもの",
    "みずぎ",
    "みつば"
  ],
  "む": [
    "むし",
    "むぎ",
    "むね",
    "むかし",
    "むすめ",
    "むすこ",
    "むらさき",
    "むしろ",
    "むしめがね",
    "むしば",
    "むちゅう",
    "むいか",
    "むだ",
    "むかで",
    "むぎわらぼうし",
    "むそう",
    "むひょう",
    "むかいがわ",
    "むすびめ",
    "むほう",
    "むちうち",
    "むめい",
    "むしくい",
    "むきず",
    "むよう"
  ],
  "め": [
    "めがね",
    "めだま",
    "めいろ",
    "めした",
    "めばえ",
    "めいし",
    "めいれい",
    "めだか",
    "めいわく",
    "めまい",
    "めやす",
    "めいぶつ",
    "めざまし",
    "めんせつ",
    "めいさく",
    "めきしこ",
    "めうえ",
    "めじるし",
    "めいさい",
    "めいちゅう",
    "めんぼく",
    "めんどう",
    "めいよ",
    "めいろう",
    "めうつり"
  ],
  "も": [
    "もも",
    "もり",
    "もち",
    "もくば",
    "もくようび",
    "もうふ",
    "もじ",
    "もみじ",
    "ももいろ",
    "もんだい",
    "もくてき",
    "もぐら",
    "もちつき",
    "もくざい",
    "もちごめ",
    "もんごる",
    "もちぬし",
    "もくじ",
    "もちば",
    "もめごと",
    "もちより",
    "もくひょう",
    "もんく",
    "もえがら",
    "もちこみ"
  ],
  "や": [
    "やま",
    "やさい",
    "やね",
    "やど",
    "やぎ",
    "やきゅう",
    "やくそく",
    "やおや",
    "やすみ",
    "やじるし",
    "やすうり",
    "やちょう",
    "やこう",
    "やしき",
    "やさしさ",
    "やきもの",
    "やまみち",
    "やえば",
    "やきそば",
    "やきいも",
    "やもり",
    "やまざと",
    "やしょく",
    "やせい",
    "やくわり"
  ],
  "ゆ": [
    "ゆき",
    "ゆめ",
    "ゆび",
    "ゆか",
    "ゆげ",
    "ゆびわ",
    "ゆうひ",
    "ゆうがた",
    "ゆうえんち",
    "ゆうびんきょく",
    "ゆうき",
    "ゆうれい",
    "ゆかた",
    "ゆのみ",
    "ゆそう",
    "ゆうしょく",
    "ゆうしょう",
    "ゆうぐれ",
    "ゆらい",
    "ゆにゅう",
    "ゆしゅつ",
    "ゆうわく",
    "ゆうじょう",
    "ゆたんぽ",
    "ゆみ",
    "ゆみや",
    "ゆうぼく",
    "ゆうやけ",
    "ゆうこう",
    "ゆだち",
    "ゆのはな",
    "ゆうめい",
    "ゆうびんうけ",
    "ゆかした",
    "ゆきどけ",
    "ゆうぐ",
    "ゆかい",
    "ゆうし"
  ],
  "よ": [
    "よる",
    "よこ",
    "よふかし",
    "よあけ",
    "よそう",
    "よしゅう",
    "よくじつ",
    "よぼう",
    "よぞら",
    "よつかど",
    "よち",
    "よわむし",
    "よふけ",
    "よてい",
    "よくばり",
    "ようき",
    "ようじ",
    "ようきゅう",
    "よこがき",
    "よろこび",
    "よあそび",
    "よかぜ",
    "よちょう",
    "ようふく",
    "よそもの"
  ],
  "ら": [
    "らくがき",
    "らくご",
    "らくよう",
    "らくだ",
    "らっぱ",
    "らいめい",
    "らんぼう",
    "らくのう",
    "らじお",
    "らんち",
    "らいぶ",
    "らんにゅう",
    "らんぷ",
    "らいこう",
    "らくらい",
    "らいはい",
    "らんそう",
    "らんきりゅう",
    "らんし",
    "らくじつ",
    "らいしゅう",
    "らいじょう",
    "らんおう",
    "らおす",
    "らいう",
    "らいと",
    "らいふる",
    "らむね",
    "らちがい",
    "らくてんしゅぎ",
    "らいばる",
    "らんちゅう"
  ],
  "り": [
    "りんご",
    "りゆう",
    "りす",
    "りか",
    "りかい",
    "りそう",
    "りゅうがく",
    "りょうり",
    "りょうて",
    "りくじょう",
    "りそく",
    "りゅうこう",
    "りえき",
    "りんぎょう",
    "りょかく",
    "りくつ",
    "りゅういき",
    "りゅうせい",
    "りゅうつう",
    "りょういき",
    "りょひ",
    "りんじ",
    "りきし",
    "りしゅう",
    "りこう",
    "りびあ",
    "りゅうがくせい",
    "りっぱ",
    "りんかく",
    "りゆうづけ",
    "りゅうすい",
    "りせい",
    "りかがく",
    "りゅうし",
    "りくあげ"
  ],
  "る": [
    "るす",
    "るいじ",
    "るいけい",
    "るいすい",
    "るいご",
    "るいじせい",
    "るいべつ",
    "るいれい",
    "るいせき",
    "るうまにあ",
    "るり",
    "るふ"
  ],
  "れ": [
    "れい",
    "れいぞうこ",
    "れきし",
    "れんしゅう",
    "れんらく",
    "れいがい",
    "れいぎ",
    "れんきんじゅつ",
    "れんが",
    "れんあい",
    "れいとうこ",
    "れんきゅう",
    "れいせい",
    "れいすい",
    "れんめい",
    "れんぞく",
    "れんじつ",
    "れんたい",
    "れいのう",
    "れきだい",
    "れんごう",
    "れんさ",
    "れいぞうしつ",
    "れっとう",
    "れいとう",
    "れんぽう",
    "れきしか",
    "れいこく",
    "れんそう",
    "れいぞう",
    "れんさい",
    "れんけい"
  ],
  "ろ": [
    "ろうか",
    "ろば",
    "ろうそく",
    "ろじ",
    "ろうご",
    "ろうどう",
    "ろてんぶろ",
    "ろうにゃく",
    "ろうれい",
    "ろんり",
    "ろうひ",
    "ろうすい",
    "ろとう",
    "ろじうら",
    "ろうきゅうか",
    "ろんそう",
    "ろしあ",
    "ろくが",
    "ろじょう",
    "ろうし",
    "ろか",
    "ろうや",
    "ろんぎ"
  ],
  "わ": [
    "わたし",
    "わに",
    "わた",
    "わすれもの",
    "わかば",
    "わかもの",
    "わかれ",
    "わりばし",
    "わたあめ",
    "わがし",
    "わふく",
    "わりびき",
    "わかて",
    "わくせい",
    "わかめ",
    "わがまま",
    "わかぎ",
    "わかどり",
    "わりあい",
    "わるくち",
    "わこうど",
    "わたりどり",
    "わりまえ"
  ],
  "が": [
    "がっこう",
    "がか",
    "がいこく",
    "がくせい",
    "がいとう",
    "がぞう",
    "がくふ",
    "がっき",
    "がびょう",
    "がいしゅつ",
    "がんぐ",
    "がくれき",
    "がいしょく",
    "がいぶ",
    "がっきゅう",
    "がいらいご",
    "がっぺい",
    "がっしょう",
    "がっさく",
    "がくせつ",
    "がっしゅく"
  ],
  "ぎ": [
    "ぎんこう",
    "ぎゅうにゅう",
    "ぎじゅつ",
    "ぎんいろ",
    "ぎゅうにく",
    "ぎせい",
    "ぎかい",
    "ぎり",
    "ぎしき",
    "ぎじろく",
    "ぎむ",
    "ぎょうれつ",
    "ぎょぎょう",
    "ぎんが",
    "ぎゃく",
    "ぎだい",
    "ぎこう",
    "ぎたい",
    "ぎわく",
    "ぎょうじ",
    "ぎょうむ"
  ],
  "ぐ": [
    "ぐあい",
    "ぐんて",
    "ぐんたい",
    "ぐたい",
    "ぐうすう",
    "ぐんしゅう",
    "ぐらす",
    "ぐち",
    "ぐんぷく",
    "ぐんしゅく",
    "ぐたいれい",
    "ぐんび",
    "ぐんじ",
    "ぐそく",
    "ぐんらく",
    "ぐそくむし",
    "ぐんゆう",
    "ぐたいか",
    "ぐんし",
    "ぐんとう"
  ],
  "げ": [
    "げんき",
    "げつようび",
    "げか",
    "げすい",
    "げんば",
    "げんこう",
    "げんそう",
    "げしゅく",
    "げんじつ",
    "げんだい",
    "げねつ",
    "げいじゅつ",
    "げいのう",
    "げっきゅう",
    "げすいどう",
    "げきじょう",
    "げんてい",
    "げんしょう",
    "げんし",
    "げんそく"
  ],
  "ご": [
    "ごみ",
    "ごかい",
    "ごらく",
    "ごうけい",
    "ごぼう",
    "ごちそう",
    "ごうい",
    "ごうどう",
    "ごかく",
    "ごぶさた",
    "ごうりゅう",
    "ごうう",
    "ごうせい",
    "ごうりか",
    "ごしょく",
    "ごうかく",
    "ごじゅう",
    "ごうか",
    "ごい",
    "ごさ"
  ],
  "ざ": [
    "ざる",
    "ざせき",
    "ざいりょう",
    "ざっし",
    "ざせつ",
    "ざつがく",
    "ざつむ",
    "ざいこ",
    "ざいばつ",
    "ざいたく",
    "ざんぎょう",
    "ざつよう",
    "ざんてい",
    "ざひょう",
    "ざんだか",
    "ざんびあ",
    "ざんこく",
    "ざこ"
  ],
  "じ": [
    "じゃがいも",
    "じゆう",
    "じかんわり",
    "じゅぎょう",
    "じゅんび",
    "じゅうたい",
    "じこ",
    "じゅうどう",
    "じっさい",
    "じかんひょう",
    "じゅうたく",
    "じゅうりょく",
    "じつりょく",
    "じゅうしょう",
    "じっしゅう",
    "じゃまいか",
    "じこく",
    "じばら",
    "じつぎょうか",
    "じゅうし"
  ],
  "ず": [
    "ずが",
    "ずつう",
    "ずのう",
    "ずるさ",
    "ずいひつ",
    "ずかい",
    "ずせつ",
    "ずひょう",
    "ずけい",
    "ずじょう",
    "ずいいち",
    "ずぼし",
    "ずいじ",
    "ずるやすみ",
    "ずいこう"
  ],
  "ぜ": [
    "ぜんかい",
    "ぜんぶ",
    "ぜつぼう",
    "ぜんこく",
    "ぜんき",
    "ぜいたく",
    "ぜっけい",
    "ぜんそく",
    "ぜつめつ",
    "ぜんい",
    "ぜんじつ",
    "ぜんと",
    "ぜっきょう",
    "ぜんりょく",
    "ぜんてい",
    "ぜひ",
    "ぜんご",
    "ぜっこう",
    "ぜんぱい"
  ],
  "ぞ": [
    "ぞう",
    "ぞうき",
    "ぞうげ",
    "ぞくご",
    "ぞうか",
    "ぞうすい",
    "ぞうほ",
    "ぞうきばやし",
    "ぞくせい",
    "ぞくとう",
    "ぞくしゅつ"
  ],
  "だ": [
    "だんぼう",
    "だいがく",
    "だんろ",
    "だいどころ",
    "だえき",
    "だんたい",
    "だいひょう",
    "だんかい",
    "だいじ",
    "だいず",
    "だぼく",
    "だんすい",
    "だんてい",
    "だいたすう",
    "だいちょう",
    "だっきゃく",
    "だんち",
    "だいく",
    "だんし",
    "だいがくせい"
  ],
  "ぢ": [],
  "づ": [],
  "で": [
    "でんき",
    "でぐち",
    "でんわ",
    "でんとう",
    "でこぼこ",
    "でんし",
    "でんぽう",
    "でんきゅう",
    "でむかえ",
    "でんたく",
    "でんきや",
    "でんちゅう",
    "でんぱ",
    "でんせつ",
    "でんたつ",
    "でんまあく",
    "でんりゅう",
    "でんきだい",
    "でんそう"
  ],
  "ど": [
    "どうぶつ",
    "どろ",
    "どうぐ",
    "どようび",
    "どうわ",
    "どうろ",
    "どりょく",
    "どひょう",
    "どうきゅうせい",
    "どうさ",
    "どうにゅう",
    "どうめい",
    "どうよう",
    "どくりつ",
    "どだい",
    "どいつ",
    "どうじょう",
    "どうさつ",
    "どうぐばこ",
    "どて"
  ],
  "ば": [
    "ばら",
    "ばんごう",
    "ばんぐみ",
    "ばくはつ",
    "ばいう",
    "ばんざい",
    "ばいばい",
    "ばんそうこう",
    "ばくが",
    "ばくちく",
    "ばいすう",
    "ばいしょう",
    "ばくろ",
    "ばいかい",
    "ばくふう",
    "ばんそう",
    "ばくしょう",
    "ばくは",
    "ばくげき",
    "ばんち"
  ],
  "び": [
    "びじゅつ",
    "びわ",
    "びせいぶつ",
    "びしょう",
    "びよう",
    "びちく",
    "びこう",
    "びんぼう",
    "びんづめ",
    "びょうき",
    "びょうどう",
    "びさい",
    "びりゅうし",
    "びょうとう",
    "びょうしつ",
    "びみょう",
    "びより",
    "びいだま"
  ],
  "ぶ": [
    "ぶた",
    "ぶんしょう",
    "ぶどう",
    "ぶんぼうぐ",
    "ぶんか",
    "ぶそう",
    "ぶんめい",
    "ぶんるい",
    "ぶかつ",
    "ぶんぽう",
    "ぶんたい",
    "ぶそく",
    "ぶき",
    "ぶんせき",
    "ぶんぱい",
    "ぶんかざい",
    "ぶたにく",
    "ぶんかい"
  ],
  "べ": [
    "べんとう",
    "べんきょう",
    "べにいろ",
    "べんぴ",
    "べっそう",
    "べつめい",
    "べんかい",
    "べんとうばこ",
    "べつわく",
    "べんごし",
    "べんしょう",
    "べんとうや",
    "べにばな",
    "べつり",
    "べにしょうが",
    "べんり",
    "べんめい",
    "べつむね"
  ],
  "ぼ": [
    "ぼうし",
    "ぼうえんきょう",
    "ぼくじょう",
    "ぼうさい",
    "ぼうねんかい",
    "ぼうふう",
    "ぼしゅう",
    "ぼうえき",
    "ぼひょう",
    "ぼち",
    "ぼうりょく",
    "ぼうすい",
    "ぼうそう",
    "ぼうはてい",
    "ぼつらく",
    "ぼうか",
    "ぼうふうう",
    "ぼうがい"
  ],
  "ぱ": [
    "ぱんや",
    "ぱんつ",
    "ぱいなっぷる",
    "ぱずる",
    "ぱんくず",
    "ぱんだ",
    "ぱじゃま",
    "ぱせり",
    "ぱらそる",
    "ぱんち",
    "ぱねる",
    "ぱいぷ",
    "ぱなま",
    "ぱすた",
    "ぱんこ",
    "ぱれっと",
    "ぱいろっと",
    "ぱんふれっと",
    "ぱぴるす"
  ],
  "ぴ": [
    "ぴあの",
    "ぴざ",
    "ぴくにっく",
    "ぴらみっど",
    "ぴんく",
    "ぴあす",
    "ぴすとる",
    "ぴりおど",
    "ぴえろ",
    "ぴあにすと",
    "ぴくるす",
    "ぴあにか",
    "ぴらふ"
  ],
  "ぷ": [
    "ぷれぜんと",
    "ぷらす",
    "ぷろぐらむ",
    "ぷらぐ",
    "ぷらねたりうむ",
    "ぷりんと",
    "ぷろぺら",
    "ぷろじぇくと",
    "ぷろとたいぷ",
    "ぷらすちっく",
    "ぷりぺいど"
  ],
  "ぺ": [
    "ぺんき",
    "ぺんだんと",
    "ぺっと",
    "ぺだる",
    "ぺいじ",
    "ぺんきや"
  ],
  "ぽ": [
    "ぽけっと",
    "ぽすと",
    "ぽいんと",
    "ぽんぷ",
    "ぽろしゃつ",
    "ぽけべる",
    "ぽうらんど",
    "ぽんこつ",
    "ぽりばけつ"
  ]
}
